[{"__type__":"cc.SpriteFrame","content":{"name":"ball_5","texture":"28I1LcRqhFr5oAhg76U01f","rect":[5,461,104,104],"offset":[0,0],"originalSize":[104,104],"capInsets":[0,0,0,0]}},{"__type__":"cc.SpriteFrame","content":{"name":"ball_8","texture":"28I1LcRqhFr5oAhg76U01f","rect":[5,803,104,104],"offset":[0,0],"originalSize":[104,104],"capInsets":[0,0,0,0]}},{"__type__":"cc.SpriteFrame","content":{"name":"ball_1","texture":"28I1LcRqhFr5oAhg76U01f","rect":[5,5,104,104],"offset":[0,0],"originalSize":[104,104],"capInsets":[0,0,0,0]}},{"__type__":"cc.SpriteFrame","content":{"name":"ball_2","texture":"28I1LcRqhFr5oAhg76U01f","rect":[5,119,104,104],"offset":[0,0],"originalSize":[104,104],"capInsets":[0,0,0,0]}},{"__type__":"cc.SpriteFrame","content":{"name":"ball_3","texture":"28I1LcRqhFr5oAhg76U01f","rect":[5,233,104,104],"offset":[0,0],"originalSize":[104,104],"capInsets":[0,0,0,0]}},{"__type__":"cc.SpriteFrame","content":{"name":"ball_6","texture":"28I1LcRqhFr5oAhg76U01f","rect":[5,575,104,104],"offset":[0,0],"originalSize":[104,104],"capInsets":[0,0,0,0]}},{"__type__":"cc.SpriteFrame","content":{"name":"ball_7","texture":"28I1LcRqhFr5oAhg76U01f","rect":[5,689,104,104],"offset":[0,0],"originalSize":[104,104],"capInsets":[0,0,0,0]}},{"__type__":"cc.SpriteFrame","content":{"name":"ball_4","texture":"28I1LcRqhFr5oAhg76U01f","rect":[5,347,104,104],"offset":[0,0],"originalSize":[104,104],"capInsets":[0,0,0,0]}},{"__type__":"cc.SpriteFrame","content":{"name":"ball_9","texture":"28I1LcRqhFr5oAhg76U01f","rect":[119,5,104,104],"offset":[0,0],"originalSize":[104,104],"capInsets":[0,0,0,0]}},{"__type__":"cc.SpriteAtlas","_name":"ballImg.plist","_spriteFrames":{"ball_1":{"__uuid__":"4dTR1DdCxODpnZIKCgbWUp"},"ball_2":{"__uuid__":"57AGoo99hDi7xdYvrotpn0"},"ball_3":{"__uuid__":"5dTIaoyUpGMb4TkMTJ1CBr"},"ball_4":{"__uuid__":"cdUvVV5MVEaJoFG6BzVdmj"},"ball_5":{"__uuid__":"10ouKWNb1PVJUc5mT9WjED"},"ball_6":{"__uuid__":"85OZ6NMt5LhbJ4AzFEDMM+"},"ball_7":{"__uuid__":"86i8s9/p9Jwp+jczFNAGcp"},"ball_8":{"__uuid__":"2dvsv0pbhPcaq6ZnjifFNI"},"ball_9":{"__uuid__":"d7rdsJUOtND7iyhGeDFLmo"}}}]